django_multisafepay/__init__.py
django_multisafepay/appsettings.py
django_multisafepay/client.py
django_multisafepay/exceptions.py
django_multisafepay/signals.py
django_multisafepay/urls.py
django_multisafepay/views.py
django_multisafepay/data/__init__.py
django_multisafepay/data/base.py
django_multisafepay/data/cart.py
django_multisafepay/data/customer.py
django_multisafepay/data/gateway.py
django_multisafepay/data/gatewayinfo.py
django_multisafepay/data/merchant.py
django_multisafepay/data/status.py
django_multisafepay/data/transaction.py
django_multisafepay/messages/__init__.py
django_multisafepay/messages/base.py
django_multisafepay/messages/checkouttransaction.py
django_multisafepay/messages/directtransaction.py
django_multisafepay/messages/gateway.py
django_multisafepay/messages/redirecttransaction.py
django_multisafepay/messages/status.py
django_multisafepay-1.1.1.dist-info/METADATA
django_multisafepay-1.1.1.dist-info/RECORD
django_multisafepay-1.1.1.dist-info/WHEEL
django_multisafepay-1.1.1.dist-info/top_level.txt
